[

  {
    "Id": "deer",
    "RaceName": "Deer",
    "NamePlural": "Deers",
    "Adjective": "deer",
    "Description": "A medium-sized hoofed forest creature that grows its antlers back each year.",
    "RaceGlyph": "D",
    "RaceForeground": "LightBrown",
    "RaceBackground": "Black",
    "ChildVolume": 14000,
    "MidVolume": 70000,
    "MaxVolume": 140000,
    "LifespanMax": 30,
    "LifespanMin": 20,
    "ChildAge": 0,
    "ChildName": "Puppy",
    "AdulthoodAge": 1,
    "RaceViewRadius": 15,
    "BaseStrenght": 10,
    "BaseToughness": 8,
    "BaseEndurance": 13,
    "BaseInt": 5,
    "BaseWillPower": 8,
    "BasePrecision": 0,
    "GeneralSpeed": 2.0,
    "BaseManaRegen": 0.05,
    "BaseMagicResistance": 1,
    "RaceNormalLimbRegen": 0.6,
    "BleedRegenaration": 0.6,
    "BodyPlan": [ "quadruped_hoof", "animal_tail", "humanoid_organs" ],
    "Tissues": [ "fur", "skin", "fat", "muscle", "bone" ],
    "HeightModifier": [ 75, 95, 98, 100, 102, 105, 125 ],
    "BroadnessModifier": [ 75, 95, 98, 100, 102, 105, 125 ],
    "Genders": [ "Male", "Female" ],
    "CreatureClass": [ "Mammal", "General" ],
    "Flags": [ "Animal", "Diurnal", "Wild", "Pet", "Grazer" ],
    "Select": [
      {
        "Selector": [ { "Genders": "Male" } ],
        "Change": "BodyPlan",
        "To": [ "quadruped_hoof", "animal_tail", "humanoid_organs", "2head_horns" ]
      },
      {
        "Selector": [ { "LimbType": "Horn" } ],
        "Change": "LastBodyPartName",
        "To": [ "{0} Antler" ]
      },
      {
        "Selector": [ { "LimbType": "Foot" } ],
        "Change": "Material",
        "To": [ "hoof_mat" ]
      }
    ]
  },
  {
    "Id": "wolf",
    "RaceName": "Wolf",
    "NamePlural": "Wolves",
    "Adjective": "cunning",
    "Description": "A large canine found in temperate regions. It is territorial and hunts in packs.",
    "RaceGlyph": "w",
    "RaceForeground": "White",
    "RaceBackground": "Grey",
    "ChildVolume": 4000,
    "MidVolume": 20000,
    "MaxVolume": 40000,
    "LifespanMax": 20,
    "LifespanMin": 10,
    "ChildAge": 0,
    "ChildName": "Puppy",
    "AdulthoodAge": 1,
    "RaceViewRadius": 15,
    "BaseStrenght": 8,
    "BaseToughness": 9,
    "BaseEndurance": 12,
    "BaseInt": 7,
    "BaseWillPower": 12,
    "BasePrecision": 2,
    "GeneralSpeed": 1.8,
    "BaseManaRegen": 0.10,
    "BaseMagicResistance": 4,
    "RaceNormalLimbRegen": 0.7,
    "BleedRegenaration": 0.7,
    "BodyPlan": [ "quadruped_limbs", "animal_tail", "humanoid_organs", "4toes" ],
    "Tissues": [ "fur", "skin", "fat", "muscle", "bone" ],
    "HeightModifier": [ 75, 95, 98, 100, 102, 105, 125 ],
    "BroadnessModifier": [ 75, 95, 98, 100, 102, 105, 125 ],
    "Genders": [ "Male", "Female" ],
    "CreatureClass": [ "Mammal", "General" ],
    "Flags": [ "Diurnal", "Wild", "Pet", "Hunter", "PackAnimal" ]
  }
]